petstore_test_9_api_client/__init__.py
petstore_test_9_api_client/api_client.py
petstore_test_9_api_client/api_response.py
petstore_test_9_api_client/configuration.py
petstore_test_9_api_client/exceptions.py
petstore_test_9_api_client/py.typed
petstore_test_9_api_client/rest.py
petstore_test_9_api_client/api/__init__.py
petstore_test_9_api_client/api/pet_api.py
petstore_test_9_api_client/api/store_api.py
petstore_test_9_api_client/api/user_api.py
petstore_test_9_api_client/models/__init__.py
petstore_test_9_api_client/models/address.py
petstore_test_9_api_client/models/api_response.py
petstore_test_9_api_client/models/category.py
petstore_test_9_api_client/models/customer.py
petstore_test_9_api_client/models/order.py
petstore_test_9_api_client/models/pet.py
petstore_test_9_api_client/models/tag.py
petstore_test_9_api_client/models/user.py
petstore_test_9_api_client-1.0.0.dist-info/METADATA
petstore_test_9_api_client-1.0.0.dist-info/WHEEL
petstore_test_9_api_client-1.0.0.dist-info/top_level.txt
petstore_test_9_api_client-1.0.0.dist-info/RECORD
